polvosetups/__init__.py
polvosetups/_modidx.py
polvosetups/core.py
polvosetups-0.0.1.dist-info/LICENSE
polvosetups-0.0.1.dist-info/METADATA
polvosetups-0.0.1.dist-info/WHEEL
polvosetups-0.0.1.dist-info/entry_points.txt
polvosetups-0.0.1.dist-info/top_level.txt
polvosetups-0.0.1.dist-info/RECORD
